{
	"resources": [{
		"name": "Component-dbg.js",
		"isDebug": true
	}, {
		"name": "Component-preload.js",
		"merged": true
	}, {
		"name": "Component.js"
	}, {
		"name": "Docs/CV_Adrien_Ratsi.pdf"
	}, {
		"name": "Docs/CV_Adrien_Ratsi.pdf"
	}, {
		"name": "Docs/documentation_technique_hu_sap.pdf"
	}, {
		"name": "Docs/documentation_technique_hu_sap_EN.pdf"
	}, {
		"name": "Images/Moi.jpg"
	}, {
		"name": "Images/agessa.png"
	}, {
		"name": "Images/assas.png"
	}, {
		"name": "Images/augustareeves_logo.png"
	}, {
		"name": "Images/autonomy.jpg"
	}, {
		"name": "Images/avis.png"
	}, {
		"name": "Images/blog.png"
	}, {
		"name": "Images/cacib_logo.png"
	}, {
		"name": "Images/cockpit.png"
	}, {
		"name": "Images/custom_field.png"
	}, {
		"name": "Images/em.png"
	}, {
		"name": "Images/en_flag.jpg"
	}, {
		"name": "Images/etiquette.png"
	}, {
		"name": "Images/flexibility.jpg"
	}, {
		"name": "Images/fr_flag.jpg"
	}, {
		"name": "Images/html_css_js_logo.png"
	}, {
		"name": "Images/intech.png"
	}, {
		"name": "Images/intechinfoesieagroupe.png"
	}, {
		"name": "Images/intranet.png"
	}, {
		"name": "Images/iut_descartes.png"
	}, {
		"name": "Images/iut_villetaneuse.png"
	}, {
		"name": "Images/java_php.png"
	}, {
		"name": "Images/lycee_newton.png"
	}, {
		"name": "Images/metalogic_logo.jpg"
	}, {
		"name": "Images/mysql.png"
	}, {
		"name": "Images/php_logo.png"
	}, {
		"name": "Images/portfolio.png"
	}, {
		"name": "Images/sap_logo.png"
	}, {
		"name": "Images/sapui5_logo.png"
	}, {
		"name": "Images/show.jpg"
	}, {
		"name": "Images/sm.png"
	}, {
		"name": "Images/synvance_logo.png"
	}, {
		"name": "Images/testimony1.png"
	}, {
		"name": "Images/testimony2.png"
	}, {
		"name": "Images/transfer.jpg"
	}, {
		"name": "Images/transmission.jpg"
	}, {
		"name": "Images/tuteur_testimony2.png"
	}, {
		"name": "Images/uipath_logo.png"
	}, {
		"name": "Images/zenity_logo.png"
	}, {
		"name": "controller/Accueil-dbg.controller.js",
		"isDebug": true
	}, {
		"name": "controller/Accueil.controller.js"
	}, {
		"name": "controller/App-dbg.controller.js",
		"isDebug": true
	}, {
		"name": "controller/App.controller.js"
	}, {
		"name": "controller/Autonomie-dbg.controller.js",
		"isDebug": true
	}, {
		"name": "controller/Autonomie.controller.js"
	}, {
		"name": "controller/BaseController-dbg.js",
		"isDebug": true
	}, {
		"name": "controller/BaseController.js"
	}, {
		"name": "controller/Flexibilite-dbg.controller.js",
		"isDebug": true
	}, {
		"name": "controller/Flexibilite.controller.js"
	}, {
		"name": "controller/HtmlCssJavascript-dbg.controller.js",
		"isDebug": true
	}, {
		"name": "controller/HtmlCssJavascript.controller.js"
	}, {
		"name": "controller/JavaPhp-dbg.controller.js",
		"isDebug": true
	}, {
		"name": "controller/JavaPhp.controller.js"
	}, {
		"name": "controller/Presenter-dbg.controller.js",
		"isDebug": true
	}, {
		"name": "controller/Presenter.controller.js"
	}, {
		"name": "controller/Rpa-dbg.controller.js",
		"isDebug": true
	}, {
		"name": "controller/Rpa.controller.js"
	}, {
		"name": "controller/Sap-dbg.controller.js",
		"isDebug": true
	}, {
		"name": "controller/Sap.controller.js"
	}, {
		"name": "controller/Sql-dbg.controller.js",
		"isDebug": true
	}, {
		"name": "controller/Sql.controller.js"
	}, {
		"name": "controller/TechnoSap-dbg.controller.js",
		"isDebug": true
	}, {
		"name": "controller/TechnoSap.controller.js"
	}, {
		"name": "controller/Transmettre-dbg.controller.js",
		"isDebug": true
	}, {
		"name": "controller/Transmettre.controller.js"
	}, {
		"name": "css/style-dbg.css",
		"isDebug": true
	}, {
		"name": "css/style.css"
	}, {
		"name": "di.code-validation.core_issues.json"
	}, {
		"name": "i18n/i18n.properties",
		"raw": "i18n/i18n.properties"
	}, {
		"name": "i18n/i18n_en_EN.properties",
		"raw": "i18n/i18n.properties",
		"locale": "_en_EN"
	}, {
		"name": "i18n/i18n_fr_FR.properties",
		"raw": "i18n/i18n.properties",
		"locale": "_fr_FR"
	}, {
		"name": "index.html"
	}, {
		"name": "manifest.json"
	}, {
		"name": "model/competence_hum.json"
	}, {
		"name": "model/competence_hum_en.json"
	}, {
		"name": "model/competence_tech.json"
	}, {
		"name": "model/competence_tech_en.json"
	}, {
		"name": "model/experience.json"
	}, {
		"name": "model/experience_en.json"
	}, {
		"name": "model/formation.json"
	}, {
		"name": "model/formation_en.json"
	}, {
		"name": "model/formatter-dbg.js",
		"isDebug": true
	}, {
		"name": "model/formatter.js"
	}, {
		"name": "model/general.json"
	}, {
		"name": "model/general_en.json"
	}, {
		"name": "model/models-dbg.js",
		"isDebug": true
	}, {
		"name": "model/models.js"
	}, {
		"name": "model/realisation.json"
	}, {
		"name": "model/realisation_en.json"
	}, {
		"name": "model/sap.json"
	}, {
		"name": "model/sap_en.json"
	}, {
		"name": "model/temoignage.json"
	}, {
		"name": "model/temoignage_en.json"
	}, {
		"name": "neo-app.json"
	}, {
		"name": "tmp/Component-preload.js",
		"merged": true
	}, {
		"name": "tmp/Component.js"
	}, {
		"name": "tmp/Docs/CV_Adrien_Ratsi.pdf"
	}, {
		"name": "tmp/Docs/CV_Adrien_Ratsi.pdf"
	}, {
		"name": "tmp/Docs/documentation_technique_hu_sap.pdf"
	}, {
		"name": "tmp/Docs/documentation_technique_hu_sap_EN.pdf"
	}, {
		"name": "tmp/Images/Moi.jpg"
	}, {
		"name": "tmp/Images/agessa.png"
	}, {
		"name": "tmp/Images/assas.png"
	}, {
		"name": "tmp/Images/augustareeves_logo.png"
	}, {
		"name": "tmp/Images/autonomy.jpg"
	}, {
		"name": "tmp/Images/avis.png"
	}, {
		"name": "tmp/Images/blog.png"
	}, {
		"name": "tmp/Images/cacib_logo.png"
	}, {
		"name": "tmp/Images/cockpit.png"
	}, {
		"name": "tmp/Images/custom_field.png"
	}, {
		"name": "tmp/Images/em.png"
	}, {
		"name": "tmp/Images/en_flag.jpg"
	}, {
		"name": "tmp/Images/etiquette.png"
	}, {
		"name": "tmp/Images/flexibility.jpg"
	}, {
		"name": "tmp/Images/fr_flag.jpg"
	}, {
		"name": "tmp/Images/html_css_js_logo.png"
	}, {
		"name": "tmp/Images/intech.png"
	}, {
		"name": "tmp/Images/intechinfoesieagroupe.png"
	}, {
		"name": "tmp/Images/intranet.png"
	}, {
		"name": "tmp/Images/iut_descartes.png"
	}, {
		"name": "tmp/Images/iut_villetaneuse.png"
	}, {
		"name": "tmp/Images/java_php.png"
	}, {
		"name": "tmp/Images/lycee_newton.png"
	}, {
		"name": "tmp/Images/metalogic_logo.jpg"
	}, {
		"name": "tmp/Images/mysql.png"
	}, {
		"name": "tmp/Images/php_logo.png"
	}, {
		"name": "tmp/Images/portfolio.png"
	}, {
		"name": "tmp/Images/sap_logo.png"
	}, {
		"name": "tmp/Images/sapui5_logo.png"
	}, {
		"name": "tmp/Images/show.jpg"
	}, {
		"name": "tmp/Images/sm.png"
	}, {
		"name": "tmp/Images/synvance_logo.png"
	}, {
		"name": "tmp/Images/testimony1.png"
	}, {
		"name": "tmp/Images/testimony2.png"
	}, {
		"name": "tmp/Images/transfer.jpg"
	}, {
		"name": "tmp/Images/transmission.jpg"
	}, {
		"name": "tmp/Images/tuteur_testimony2.png"
	}, {
		"name": "tmp/Images/uipath_logo.png"
	}, {
		"name": "tmp/Images/zenity_logo.png"
	}, {
		"name": "tmp/controller/Accueil.controller.js"
	}, {
		"name": "tmp/controller/App.controller.js"
	}, {
		"name": "tmp/controller/Autonomie.controller.js"
	}, {
		"name": "tmp/controller/BaseController.js"
	}, {
		"name": "tmp/controller/Flexibilite.controller.js"
	}, {
		"name": "tmp/controller/HtmlCssJavascript.controller.js"
	}, {
		"name": "tmp/controller/JavaPhp.controller.js"
	}, {
		"name": "tmp/controller/Presenter.controller.js"
	}, {
		"name": "tmp/controller/Rpa.controller.js"
	}, {
		"name": "tmp/controller/Sap.controller.js"
	}, {
		"name": "tmp/controller/Sql.controller.js"
	}, {
		"name": "tmp/controller/TechnoSap.controller.js"
	}, {
		"name": "tmp/controller/Transmettre.controller.js"
	}, {
		"name": "tmp/css/style.css"
	}, {
		"name": "tmp/i18n/i18n.properties",
		"raw": "i18n/i18n.properties"
	}, {
		"name": "tmp/i18n/i18n_en_EN.properties",
		"raw": "i18n/i18n.properties",
		"locale": "_en_EN"
	}, {
		"name": "tmp/i18n/i18n_fr_FR.properties",
		"raw": "i18n/i18n.properties",
		"locale": "_fr_FR"
	}, {
		"name": "tmp/index.html"
	}, {
		"name": "tmp/manifest.json"
	}, {
		"name": "tmp/model/competence_hum.json"
	}, {
		"name": "tmp/model/competence_hum_en.json"
	}, {
		"name": "tmp/model/competence_tech.json"
	}, {
		"name": "tmp/model/competence_tech_en.json"
	}, {
		"name": "tmp/model/experience.json"
	}, {
		"name": "tmp/model/experience_en.json"
	}, {
		"name": "tmp/model/formation.json"
	}, {
		"name": "tmp/model/formation_en.json"
	}, {
		"name": "tmp/model/formatter.js"
	}, {
		"name": "tmp/model/general.json"
	}, {
		"name": "tmp/model/general_en.json"
	}, {
		"name": "tmp/model/models.js"
	}, {
		"name": "tmp/model/realisation.json"
	}, {
		"name": "tmp/model/realisation_en.json"
	}, {
		"name": "tmp/model/sap.json"
	}, {
		"name": "tmp/model/sap_en.json"
	}, {
		"name": "tmp/model/temoignage.json"
	}, {
		"name": "tmp/model/temoignage_en.json"
	}, {
		"name": "tmp/view/Accueil.view.xml"
	}, {
		"name": "tmp/view/App.view.xml"
	}, {
		"name": "tmp/view/Autonomie.view.xml"
	}, {
		"name": "tmp/view/Flexibilite.view.xml"
	}, {
		"name": "tmp/view/HtmlCssJavascript.view.xml"
	}, {
		"name": "tmp/view/JavaPhp.view.xml"
	}, {
		"name": "tmp/view/Presenter.view.xml"
	}, {
		"name": "tmp/view/Rpa.view.xml"
	}, {
		"name": "tmp/view/Sap.view.xml"
	}, {
		"name": "tmp/view/Sql.view.xml"
	}, {
		"name": "tmp/view/TechnoSap.view.xml"
	}, {
		"name": "tmp/view/Transmettre.view.xml"
	}, {
		"name": "tmp/view/fragment/realisation.fragment.xml"
	}, {
		"name": "tmp-dbg/Component.js"
	}, {
		"name": "tmp-dbg/controller/Accueil.controller.js"
	}, {
		"name": "tmp-dbg/controller/App.controller.js"
	}, {
		"name": "tmp-dbg/controller/Autonomie.controller.js"
	}, {
		"name": "tmp-dbg/controller/BaseController.js"
	}, {
		"name": "tmp-dbg/controller/Flexibilite.controller.js"
	}, {
		"name": "tmp-dbg/controller/HtmlCssJavascript.controller.js"
	}, {
		"name": "tmp-dbg/controller/JavaPhp.controller.js"
	}, {
		"name": "tmp-dbg/controller/Presenter.controller.js"
	}, {
		"name": "tmp-dbg/controller/Rpa.controller.js"
	}, {
		"name": "tmp-dbg/controller/Sap.controller.js"
	}, {
		"name": "tmp-dbg/controller/Sql.controller.js"
	}, {
		"name": "tmp-dbg/controller/TechnoSap.controller.js"
	}, {
		"name": "tmp-dbg/controller/Transmettre.controller.js"
	}, {
		"name": "tmp-dbg/css/style.css"
	}, {
		"name": "tmp-dbg/model/formatter.js"
	}, {
		"name": "tmp-dbg/model/models.js"
	}, {
		"name": "view/Accueil.view.xml"
	}, {
		"name": "view/App.view.xml"
	}, {
		"name": "view/Autonomie.view.xml"
	}, {
		"name": "view/Flexibilite.view.xml"
	}, {
		"name": "view/HtmlCssJavascript.view.xml"
	}, {
		"name": "view/JavaPhp.view.xml"
	}, {
		"name": "view/Presenter.view.xml"
	}, {
		"name": "view/Rpa.view.xml"
	}, {
		"name": "view/Sap.view.xml"
	}, {
		"name": "view/Sql.view.xml"
	}, {
		"name": "view/TechnoSap.view.xml"
	}, {
		"name": "view/Transmettre.view.xml"
	}, {
		"name": "view/fragment/realisation.fragment.xml"
	}]
}